{
  "monster": [
    {
      "name": "骷髅射手",
      "source": " 墓穴怪物",
      "size": "M",
      "type": "不死生物",
      "alignment": "守序邪恶",
      "ac": 16,
      "speed": {
        "walk": 30
      },
      "str": 14,
      "dex": 18,
      "con": 16,
      "int": 10,
      "wis": 14,
      "cha": 8,
      "cr": "7",
      "trait": [
        {
          "name": "誓仇弓",
          "entries": [
            "战斗开始时选择一个它能看到的敌对生物作为仇敌。对仇敌发动远程攻击时，攻击检定具有优势。目标不会从非全身掩护的状态中受益，骷髅射手也不会因为超出常规射程而承受劣势。如果攻击命中，仇敌将额外受 {@damage 3d6} 点穿刺伤害。"
          ]
        },
        {
          "name": "不死本质",
          "entries": [
            "不需要空气，饮食和睡眠。"
          ]
        }
      ],
      "action": [
        {
          "name": "多重攻击",
          "entries": [
            "发动两次射击或一次穿刺。"
          ]
        },
        {
          "name": "射击：远程武器攻击",
          "entries": [
            "{@hit 7}命中，射程 150/600 尺，单一目标。命中：{@hit 9} 造成{@damage 1d8 + 4}点 穿刺伤害，若目标是仇敌，则额外造成 {@damage 10 (3d6)}点 穿刺伤害"
          ]
        },
        {
          "name": "穿刺",
          "entries": [
            "(充能 {@recharge 5–6}),射出一支能够自动修正轨迹的箭矢，选择 60 尺内至多 2 个目标，目标进行 DC15 敏捷豁免，失败受到 {@damage 22 (4d10)} 穿刺伤害，成功则伤害减半，若其中包含仇敌目标，该目标豁免具有劣势。"
          ]
        }
      ],
      "bonus": [],
      "reaction": [],
      "legendary": [],
      "ENG_name": "Skeleton Archer",
      "hp": {
        "average": 112,
        "formula": "15d8+45"
      },
      "skill": {
        "Stealth": "+7",
        "Perception": "+5"
      },
      "resist": [
        "非魔法钝击",
        "穿刺",
        "挥砍"
      ],
      "immune": [
        "毒素"
      ],
      "vulnerable": [
        "钝击"
      ],
      "conditionImmune": [
        "中毒",
        "力竭"
      ],
      "passive": 15,
      "senses": [
        "黑暗视觉 60 尺"
      ],
      "languages": [
        "理解通用语但不能说"
      ]
    }
  ]
}